code_generator/__init__.py
code_generator/generators/cpp.py
code_generator/generators/docs.py
code_generator/test/__init__.py
code_generator/test/cpp/__init__.py
code_generator/test/cpp/test_array.py
code_generator/test/cpp/test_class.py
code_generator/test/cpp/test_enum.py
code_generator/test/cpp/test_function.py
code_generator/test/cpp/test_header.py
code_generator/test/cpp/test_source.py
code_generator/test/cpp/test_variable.py
erichschroeter.code_generator-0.1.0.dist-info/LICENSE
erichschroeter.code_generator-0.1.0.dist-info/METADATA
erichschroeter.code_generator-0.1.0.dist-info/WHEEL
erichschroeter.code_generator-0.1.0.dist-info/top_level.txt
erichschroeter.code_generator-0.1.0.dist-info/RECORD
