Metadata-Version: 2.2
Name: erichschroeter.code_generator
Version: 0.1.0
Summary: A simple code generator library
Author-email: Erich Schroeter <erich.schroeter+pypi@gmail.com>
Project-URL: Homepage, https://github.com/erichschroeter/code_generator
Project-URL: Issues, https://github.com/erichschroeter/code_generator/issues
Classifier: Programming Language :: Python :: 3
Classifier: License :: OSI Approved :: MIT License
Classifier: Operating System :: OS Independent
Classifier: Topic :: Software Development :: Code Generators
Requires-Python: >=3.9
License-File: LICENSE
Requires-Dist: Jinja2==3.1.4
Provides-Extra: test
Requires-Dist: pytest==8.3.3; extra == "test"
